arcgis_compressed_geometry/__init__.py
arcgis_compressed_geometry/arcgis_compressed_geometry.py
arcgis_compressed_geometry-0.0.2.dist-info/licenses/LICENSE
arcgis_compressed_geometry-0.0.2.dist-info/METADATA
arcgis_compressed_geometry-0.0.2.dist-info/WHEEL
arcgis_compressed_geometry-0.0.2.dist-info/top_level.txt
arcgis_compressed_geometry-0.0.2.dist-info/RECORD
