Metadata-Version: 2.4
Name: arcgis-compressed-geometry
Version: 0.0.2
Summary: A Python implementation of ESRI's ArcGIS Compressed Geometry Format.
Author-email: maslke <maslke@outlook.com>
License: MIT License
Requires-Python: >=3.7
License-File: LICENSE
Dynamic: license-file
